[{"_id":{"$oid":"636fccaefc13ae3254005287"},"name":"Rouvin Kendell","workStartTime":"2022-05-31T10:29:52Z","workFinishedTime":"2021-11-26T01:46:21Z","todayWorkTime":10,"weeklyWorkTime":28,"_class":"com.guardjo.freeworkslackbot.domain.Worker"},
  {"_id":{"$oid":"636fccaefc13ae3254005288"},"name":"Feliks Gatherer","workStartTime":"2021-12-07T12:04:38Z","workFinishedTime":"2022-01-15T13:51:56Z","todayWorkTime":10,"weeklyWorkTime":4,"_class":"com.guardjo.freeworkslackbot.domain.Worker"},
  {"_id":{"$oid":"636fccaefc13ae3254005289"},"name":"Kari Brettoner","workStartTime":"2022-06-27T22:32:22Z","workFinishedTime":"2022-05-05T14:33:28Z","todayWorkTime":6,"weeklyWorkTime":26,"_class":"com.guardjo.freeworkslackbot.domain.Worker"},
  {"_id":{"$oid":"636fccaefc13ae325400528a"},"name":"Rice Hamberston","workStartTime":"2022-08-13T16:49:38Z","workFinishedTime":"2022-01-14T03:23:45Z","todayWorkTime":9,"weeklyWorkTime":17,"_class":"com.guardjo.freeworkslackbot.domain.Worker"},
  {"_id":{"$oid":"636fccaefc13ae325400528b"},"name":"Fifi Cowan","workStartTime":"2022-06-25T10:21:37Z","workFinishedTime":"2022-10-13T07:27:51Z","todayWorkTime":9,"weeklyWorkTime":21,"_class":"com.guardjo.freeworkslackbot.domain.Worker"},
  {"_id":{"$oid":"636fccaefc13ae325400528c"},"name":"Chalmers Bunting","workStartTime":"2022-06-13T03:12:00Z","workFinishedTime":"2022-08-25T05:10:10Z","todayWorkTime":10,"weeklyWorkTime":23,"_class":"com.guardjo.freeworkslackbot.domain.Worker"},
  {"_id":{"$oid":"636fccaefc13ae325400528d"},"name":"Edie Tenant","workStartTime":"2022-04-17T05:06:16Z","workFinishedTime":"2022-08-10T12:13:18Z","todayWorkTime":6,"weeklyWorkTime":14,"_class":"com.guardjo.freeworkslackbot.domain.Worker"},
  {"_id":{"$oid":"636fccaefc13ae325400528e"},"name":"Valida Casel","workStartTime":"2021-11-27T07:31:52Z","workFinishedTime":"2022-08-04T04:17:52Z","todayWorkTime":8,"weeklyWorkTime":8,"_class":"com.guardjo.freeworkslackbot.domain.Worker"},
  {"_id":{"$oid":"636fccaefc13ae325400528f"},"name":"Nina Verden","workStartTime":"2022-09-24T14:25:55Z","workFinishedTime":"2022-02-23T10:59:30Z","todayWorkTime":10,"weeklyWorkTime":37,"_class":"com.guardjo.freeworkslackbot.domain.Worker"},
  {"_id":{"$oid":"636fccaefc13ae3254005290"},"name":"Carly Boggs","workStartTime":"2022-01-20T08:41:27Z","workFinishedTime":"2022-01-14T03:10:28Z","todayWorkTime":10,"weeklyWorkTime":33,"_class":"com.guardjo.freeworkslackbot.domain.Worker"},
  {"_id":{"$oid":"636fccaefc13ae3254005291"},"name":"Fredericka Woolforde","workStartTime":"2022-03-09T07:36:00Z","workFinishedTime":"2022-10-11T19:50:23Z","todayWorkTime":8,"weeklyWorkTime":24,"_class":"com.guardjo.freeworkslackbot.domain.Worker"},
  {"_id":{"$oid":"636fccaefc13ae3254005292"},"name":"Temp Marcroft","workStartTime":"2022-03-16T23:24:10Z","workFinishedTime":"2022-08-18T08:12:05Z","todayWorkTime":10,"weeklyWorkTime":18,"_class":"com.guardjo.freeworkslackbot.domain.Worker"},
  {"_id":{"$oid":"636fccaefc13ae3254005293"},"name":"Creighton Bernardi","workStartTime":"2021-11-24T17:30:13Z","workFinishedTime":"2022-08-29T05:51:16Z","todayWorkTime":6,"weeklyWorkTime":1,"_class":"com.guardjo.freeworkslackbot.domain.Worker"},
  {"_id":{"$oid":"636fccaefc13ae3254005294"},"name":"Byron Pike","workStartTime":"2022-02-02T10:25:48Z","workFinishedTime":"2022-09-17T18:06:31Z","todayWorkTime":6,"weeklyWorkTime":5,"_class":"com.guardjo.freeworkslackbot.domain.Worker"},
  {"_id":{"$oid":"636fccaefc13ae3254005295"},"name":"Alisun Dew","workStartTime":"2022-07-20T21:22:09Z","workFinishedTime":"2022-03-11T21:52:04Z","todayWorkTime":7,"weeklyWorkTime":8,"_class":"com.guardjo.freeworkslackbot.domain.Worker"},
  {"_id":{"$oid":"636fccaefc13ae3254005296"},"name":"Ilario Gaythorpe","workStartTime":"2022-07-03T07:49:44Z","workFinishedTime":"2021-12-15T23:47:51Z","todayWorkTime":6,"weeklyWorkTime":4,"_class":"com.guardjo.freeworkslackbot.domain.Worker"},
  {"_id":{"$oid":"636fccaefc13ae3254005297"},"name":"Adham Yellowlees","workStartTime":"2022-07-23T10:33:32Z","workFinishedTime":"2022-06-14T05:16:51Z","todayWorkTime":7,"weeklyWorkTime":37,"_class":"com.guardjo.freeworkslackbot.domain.Worker"},
  {"_id":{"$oid":"636fccaefc13ae3254005298"},"name":"Jasun Rantoul","workStartTime":"2022-01-21T08:08:50Z","workFinishedTime":"2021-12-18T14:15:19Z","todayWorkTime":7,"weeklyWorkTime":39,"_class":"com.guardjo.freeworkslackbot.domain.Worker"},
  {"_id":{"$oid":"636fccaefc13ae3254005299"},"name":"Andie Blabey","workStartTime":"2022-11-09T17:07:25Z","workFinishedTime":"2022-10-16T23:36:40Z","todayWorkTime":7,"weeklyWorkTime":19,"_class":"com.guardjo.freeworkslackbot.domain.Worker"},
  {"_id":{"$oid":"636fccaefc13ae325400529a"},"name":"Billie Mathet","workStartTime":"2022-04-15T18:19:23Z","workFinishedTime":"2022-09-27T13:54:56Z","todayWorkTime":8,"weeklyWorkTime":30,"_class":"com.guardjo.freeworkslackbot.domain.Worker"},
  {"_id":{"$oid":"636fccaefc13ae325400529b"},"name":"Frankie Lawson","workStartTime":"2021-12-19T10:33:44Z","workFinishedTime":"2022-06-22T15:31:16Z","todayWorkTime":6,"weeklyWorkTime":35,"_class":"com.guardjo.freeworkslackbot.domain.Worker"},
  {"_id":{"$oid":"636fccaffc13ae325400529c"},"name":"Jane Beevis","workStartTime":"2021-12-18T04:31:58Z","workFinishedTime":"2022-04-02T09:29:19Z","todayWorkTime":6,"weeklyWorkTime":17,"_class":"com.guardjo.freeworkslackbot.domain.Worker"},
  {"_id":{"$oid":"636fccaffc13ae325400529d"},"name":"Joseph Corona","workStartTime":"2022-05-12T12:36:48Z","workFinishedTime":"2022-02-06T14:28:20Z","todayWorkTime":8,"weeklyWorkTime":4,"_class":"com.guardjo.freeworkslackbot.domain.Worker"},
  {"_id":{"$oid":"636fccaffc13ae325400529e"},"name":"Kelsey Huc","workStartTime":"2022-04-14T01:10:11Z","workFinishedTime":"2022-06-14T20:31:17Z","todayWorkTime":8,"weeklyWorkTime":14,"_class":"com.guardjo.freeworkslackbot.domain.Worker"},
  {"_id":{"$oid":"636fccaffc13ae325400529f"},"name":"Sharline Standon","workStartTime":"2021-11-23T01:23:43Z","workFinishedTime":"2022-06-10T14:04:50Z","todayWorkTime":6,"weeklyWorkTime":26,"_class":"com.guardjo.freeworkslackbot.domain.Worker"},
  {"_id":{"$oid":"636fccaffc13ae32540052a0"},"name":"Hugues Devon","workStartTime":"2022-08-07T16:33:19Z","workFinishedTime":"2022-07-04T08:17:04Z","todayWorkTime":6,"weeklyWorkTime":35,"_class":"com.guardjo.freeworkslackbot.domain.Worker"},
  {"_id":{"$oid":"636fccaffc13ae32540052a1"},"name":"Shamus Arkin","workStartTime":"2022-08-03T19:29:23Z","workFinishedTime":"2022-01-21T18:22:56Z","todayWorkTime":7,"weeklyWorkTime":36,"_class":"com.guardjo.freeworkslackbot.domain.Worker"},
  {"_id":{"$oid":"636fccaffc13ae32540052a2"},"name":"Rosalia Salle","workStartTime":"2022-10-26T06:48:08Z","workFinishedTime":"2022-10-17T07:18:10Z","todayWorkTime":10,"weeklyWorkTime":11,"_class":"com.guardjo.freeworkslackbot.domain.Worker"},
  {"_id":{"$oid":"636fccaffc13ae32540052a3"},"name":"Faustine Vischi","workStartTime":"2022-04-02T11:47:42Z","workFinishedTime":"2021-12-27T10:21:40Z","todayWorkTime":10,"weeklyWorkTime":16,"_class":"com.guardjo.freeworkslackbot.domain.Worker"},
  {"_id":{"$oid":"636fccaffc13ae32540052a4"},"name":"Brigg Dufore","workStartTime":"2022-09-19T20:43:49Z","workFinishedTime":"2021-12-12T02:38:27Z","todayWorkTime":9,"weeklyWorkTime":35,"_class":"com.guardjo.freeworkslackbot.domain.Worker"},
  {"_id":{"$oid":"636fccaffc13ae32540052a5"},"name":"Sebastien Knee","workStartTime":"2022-02-09T21:38:15Z","workFinishedTime":"2022-06-29T13:20:05Z","todayWorkTime":8,"weeklyWorkTime":4,"_class":"com.guardjo.freeworkslackbot.domain.Worker"},
  {"_id":{"$oid":"636fccaffc13ae32540052a6"},"name":"Elwood Alvar","workStartTime":"2022-09-22T23:53:14Z","workFinishedTime":"2022-03-30T16:26:12Z","todayWorkTime":6,"weeklyWorkTime":5,"_class":"com.guardjo.freeworkslackbot.domain.Worker"},
  {"_id":{"$oid":"636fccaffc13ae32540052a7"},"name":"Karina Peepall","workStartTime":"2021-12-07T05:07:20Z","workFinishedTime":"2022-02-09T17:22:30Z","todayWorkTime":9,"weeklyWorkTime":37,"_class":"com.guardjo.freeworkslackbot.domain.Worker"},
  {"_id":{"$oid":"636fccaffc13ae32540052a8"},"name":"Cece Blei","workStartTime":"2022-11-02T14:20:31Z","workFinishedTime":"2022-01-10T06:39:18Z","todayWorkTime":6,"weeklyWorkTime":39,"_class":"com.guardjo.freeworkslackbot.domain.Worker"},
  {"_id":{"$oid":"636fccaffc13ae32540052a9"},"name":"Jennette Jeacocke","workStartTime":"2022-05-09T20:22:50Z","workFinishedTime":"2022-01-15T15:48:24Z","todayWorkTime":6,"weeklyWorkTime":25,"_class":"com.guardjo.freeworkslackbot.domain.Worker"},
  {"_id":{"$oid":"636fccaffc13ae32540052aa"},"name":"Annice Veelers","workStartTime":"2022-01-31T03:06:40Z","workFinishedTime":"2022-06-11T22:10:20Z","todayWorkTime":6,"weeklyWorkTime":0,"_class":"com.guardjo.freeworkslackbot.domain.Worker"},
  {"_id":{"$oid":"636fccaffc13ae32540052ab"},"name":"Imojean Drew-Clifton","workStartTime":"2022-08-25T20:46:50Z","workFinishedTime":"2022-09-30T09:44:35Z","todayWorkTime":7,"weeklyWorkTime":19,"_class":"com.guardjo.freeworkslackbot.domain.Worker"},
  {"_id":{"$oid":"636fccaffc13ae32540052ac"},"name":"Fifi Bambury","workStartTime":"2022-03-11T18:45:08Z","workFinishedTime":"2022-09-30T20:40:00Z","todayWorkTime":7,"weeklyWorkTime":17,"_class":"com.guardjo.freeworkslackbot.domain.Worker"},
  {"_id":{"$oid":"636fccaffc13ae32540052ad"},"name":"Graig De Gowe","workStartTime":"2022-10-19T01:33:03Z","workFinishedTime":"2022-01-12T08:44:08Z","todayWorkTime":6,"weeklyWorkTime":34,"_class":"com.guardjo.freeworkslackbot.domain.Worker"},
  {"_id":{"$oid":"636fccaffc13ae32540052ae"},"name":"Lettie Morfett","workStartTime":"2022-06-29T01:30:47Z","workFinishedTime":"2022-09-18T14:33:24Z","todayWorkTime":6,"weeklyWorkTime":2,"_class":"com.guardjo.freeworkslackbot.domain.Worker"},
  {"_id":{"$oid":"636fccaffc13ae32540052af"},"name":"Ronny Cocker","workStartTime":"2021-12-06T22:15:23Z","workFinishedTime":"2022-06-08T17:41:50Z","todayWorkTime":8,"weeklyWorkTime":0,"_class":"com.guardjo.freeworkslackbot.domain.Worker"},
  {"_id":{"$oid":"636fccaffc13ae32540052b0"},"name":"Russell Syrad","workStartTime":"2022-04-16T01:11:24Z","workFinishedTime":"2022-03-21T15:44:24Z","todayWorkTime":8,"weeklyWorkTime":7,"_class":"com.guardjo.freeworkslackbot.domain.Worker"},
  {"_id":{"$oid":"636fccaffc13ae32540052b1"},"name":"Xerxes Gudgen","workStartTime":"2022-03-26T00:33:23Z","workFinishedTime":"2022-04-19T18:20:56Z","todayWorkTime":10,"weeklyWorkTime":14,"_class":"com.guardjo.freeworkslackbot.domain.Worker"},
  {"_id":{"$oid":"636fccaffc13ae32540052b2"},"name":"Allix Touhig","workStartTime":"2022-08-30T13:19:37Z","workFinishedTime":"2022-05-28T02:46:41Z","todayWorkTime":6,"weeklyWorkTime":27,"_class":"com.guardjo.freeworkslackbot.domain.Worker"},
  {"_id":{"$oid":"636fccaffc13ae32540052b3"},"name":"Waldo Hatherley","workStartTime":"2022-07-22T12:13:29Z","workFinishedTime":"2022-04-14T03:58:27Z","todayWorkTime":6,"weeklyWorkTime":15,"_class":"com.guardjo.freeworkslackbot.domain.Worker"},
  {"_id":{"$oid":"636fccaffc13ae32540052b4"},"name":"Sela MacKaig","workStartTime":"2022-05-02T19:20:20Z","workFinishedTime":"2022-08-23T22:02:20Z","todayWorkTime":9,"weeklyWorkTime":12,"_class":"com.guardjo.freeworkslackbot.domain.Worker"},
  {"_id":{"$oid":"636fccaffc13ae32540052b5"},"name":"Dalila Haitlie","workStartTime":"2022-06-07T23:30:20Z","workFinishedTime":"2022-07-04T13:58:14Z","todayWorkTime":10,"weeklyWorkTime":30,"_class":"com.guardjo.freeworkslackbot.domain.Worker"},
  {"_id":{"$oid":"636fccaffc13ae32540052b6"},"name":"Alexandre Minogue","workStartTime":"2022-08-13T06:53:12Z","workFinishedTime":"2022-03-10T21:30:34Z","todayWorkTime":7,"weeklyWorkTime":11,"_class":"com.guardjo.freeworkslackbot.domain.Worker"},
  {"_id":{"$oid":"636fccaffc13ae32540052b7"},"name":"Joceline Brizland","workStartTime":"2022-09-19T07:11:34Z","workFinishedTime":"2021-12-15T11:22:59Z","todayWorkTime":8,"weeklyWorkTime":2,"_class":"com.guardjo.freeworkslackbot.domain.Worker"},
  {"_id":{"$oid":"636fccaffc13ae32540052b8"},"name":"Arlyn Labba","workStartTime":"2022-11-07T22:32:27Z","workFinishedTime":"2022-04-15T21:21:39Z","todayWorkTime":10,"weeklyWorkTime":30,"_class":"com.guardjo.freeworkslackbot.domain.Worker"},
  {"_id":{"$oid":"636fccaffc13ae32540052b9"},"name":"Cherrita Quye","workStartTime":"2022-05-15T18:25:05Z","workFinishedTime":"2022-06-05T22:18:42Z","todayWorkTime":9,"weeklyWorkTime":35,"_class":"com.guardjo.freeworkslackbot.domain.Worker"},
  {"_id":{"$oid":"636fccaffc13ae32540052ba"},"name":"El Have","workStartTime":"2022-05-16T13:26:10Z","workFinishedTime":"2022-03-27T19:24:24Z","todayWorkTime":10,"weeklyWorkTime":29,"_class":"com.guardjo.freeworkslackbot.domain.Worker"},
  {"_id":{"$oid":"636fccaffc13ae32540052bb"},"name":"Jocelyne Vannar","workStartTime":"2022-10-15T15:58:58Z","workFinishedTime":"2022-05-11T20:55:41Z","todayWorkTime":7,"weeklyWorkTime":32,"_class":"com.guardjo.freeworkslackbot.domain.Worker"},
  {"_id":{"$oid":"636fccaffc13ae32540052bc"},"name":"Eddy Benedick","workStartTime":"2022-06-16T16:42:58Z","workFinishedTime":"2021-12-28T08:42:18Z","todayWorkTime":6,"weeklyWorkTime":26,"_class":"com.guardjo.freeworkslackbot.domain.Worker"},
  {"_id":{"$oid":"636fccaffc13ae32540052bd"},"name":"Cristi Beckingham","workStartTime":"2022-05-09T15:04:08Z","workFinishedTime":"2022-06-16T12:53:14Z","todayWorkTime":10,"weeklyWorkTime":10,"_class":"com.guardjo.freeworkslackbot.domain.Worker"},
  {"_id":{"$oid":"636fccaffc13ae32540052be"},"name":"Lucky Slowcock","workStartTime":"2022-01-31T18:21:20Z","workFinishedTime":"2022-01-20T03:22:50Z","todayWorkTime":7,"weeklyWorkTime":19,"_class":"com.guardjo.freeworkslackbot.domain.Worker"},
  {"_id":{"$oid":"636fccaffc13ae32540052bf"},"name":"Lemar Probbings","workStartTime":"2022-10-28T01:52:45Z","workFinishedTime":"2022-09-02T09:58:11Z","todayWorkTime":6,"weeklyWorkTime":7,"_class":"com.guardjo.freeworkslackbot.domain.Worker"},
  {"_id":{"$oid":"636fccaffc13ae32540052c0"},"name":"Denys Milmith","workStartTime":"2021-12-14T10:24:54Z","workFinishedTime":"2022-07-03T20:18:42Z","todayWorkTime":10,"weeklyWorkTime":20,"_class":"com.guardjo.freeworkslackbot.domain.Worker"},
  {"_id":{"$oid":"636fccaffc13ae32540052c1"},"name":"Morgen Borit","workStartTime":"2022-11-06T21:34:13Z","workFinishedTime":"2021-12-17T12:54:50Z","todayWorkTime":6,"weeklyWorkTime":28,"_class":"com.guardjo.freeworkslackbot.domain.Worker"},
  {"_id":{"$oid":"636fccaffc13ae32540052c2"},"name":"Prentice Durker","workStartTime":"2022-07-23T00:28:20Z","workFinishedTime":"2022-10-14T15:23:56Z","todayWorkTime":6,"weeklyWorkTime":11,"_class":"com.guardjo.freeworkslackbot.domain.Worker"},
  {"_id":{"$oid":"636fccaffc13ae32540052c3"},"name":"Lauri Keuning","workStartTime":"2022-08-15T13:34:21Z","workFinishedTime":"2022-03-06T10:20:32Z","todayWorkTime":10,"weeklyWorkTime":23,"_class":"com.guardjo.freeworkslackbot.domain.Worker"},
  {"_id":{"$oid":"636fccaffc13ae32540052c4"},"name":"Teador Brantzen","workStartTime":"2022-08-15T05:17:56Z","workFinishedTime":"2021-12-02T07:02:50Z","todayWorkTime":7,"weeklyWorkTime":20,"_class":"com.guardjo.freeworkslackbot.domain.Worker"},
  {"_id":{"$oid":"636fccaffc13ae32540052c5"},"name":"Ashil Croxall","workStartTime":"2022-07-01T18:40:45Z","workFinishedTime":"2022-01-24T11:52:51Z","todayWorkTime":9,"weeklyWorkTime":1,"_class":"com.guardjo.freeworkslackbot.domain.Worker"},
  {"_id":{"$oid":"636fccaffc13ae32540052c6"},"name":"Staford Grills","workStartTime":"2022-10-13T12:09:53Z","workFinishedTime":"2022-06-29T15:42:29Z","todayWorkTime":7,"weeklyWorkTime":32,"_class":"com.guardjo.freeworkslackbot.domain.Worker"},
  {"_id":{"$oid":"636fccaffc13ae32540052c7"},"name":"Edita Blasik","workStartTime":"2022-08-13T16:01:11Z","workFinishedTime":"2022-07-29T17:35:18Z","todayWorkTime":6,"weeklyWorkTime":11,"_class":"com.guardjo.freeworkslackbot.domain.Worker"},
  {"_id":{"$oid":"636fccaffc13ae32540052c8"},"name":"Mic Clem","workStartTime":"2022-09-29T08:04:49Z","workFinishedTime":"2022-10-23T21:25:19Z","todayWorkTime":6,"weeklyWorkTime":5,"_class":"com.guardjo.freeworkslackbot.domain.Worker"},
  {"_id":{"$oid":"636fccaffc13ae32540052c9"},"name":"Woodman Charlot","workStartTime":"2022-08-09T21:35:57Z","workFinishedTime":"2022-06-23T07:19:39Z","todayWorkTime":8,"weeklyWorkTime":37,"_class":"com.guardjo.freeworkslackbot.domain.Worker"},
  {"_id":{"$oid":"636fccaffc13ae32540052ca"},"name":"Edna Hidderley","workStartTime":"2022-05-27T02:58:07Z","workFinishedTime":"2022-09-16T07:21:35Z","todayWorkTime":7,"weeklyWorkTime":34,"_class":"com.guardjo.freeworkslackbot.domain.Worker"},
  {"_id":{"$oid":"636fccaffc13ae32540052cb"},"name":"Sherwood Poate","workStartTime":"2022-08-02T20:52:10Z","workFinishedTime":"2022-03-01T08:08:47Z","todayWorkTime":8,"weeklyWorkTime":2,"_class":"com.guardjo.freeworkslackbot.domain.Worker"},
  {"_id":{"$oid":"636fccaffc13ae32540052cc"},"name":"Micky Schooley","workStartTime":"2022-06-11T14:01:42Z","workFinishedTime":"2022-06-25T19:22:14Z","todayWorkTime":6,"weeklyWorkTime":37,"_class":"com.guardjo.freeworkslackbot.domain.Worker"},
  {"_id":{"$oid":"636fccaffc13ae32540052cd"},"name":"Karee Pashba","workStartTime":"2022-08-12T17:39:08Z","workFinishedTime":"2022-04-26T21:47:40Z","todayWorkTime":9,"weeklyWorkTime":36,"_class":"com.guardjo.freeworkslackbot.domain.Worker"},
  {"_id":{"$oid":"636fccaffc13ae32540052ce"},"name":"Florenza Hedon","workStartTime":"2022-03-27T07:02:43Z","workFinishedTime":"2022-03-15T12:58:20Z","todayWorkTime":7,"weeklyWorkTime":28,"_class":"com.guardjo.freeworkslackbot.domain.Worker"},
  {"_id":{"$oid":"636fccaffc13ae32540052cf"},"name":"Frank Layburn","workStartTime":"2021-12-04T21:09:20Z","workFinishedTime":"2022-05-09T16:43:52Z","todayWorkTime":10,"weeklyWorkTime":11,"_class":"com.guardjo.freeworkslackbot.domain.Worker"},
  {"_id":{"$oid":"636fccaffc13ae32540052d0"},"name":"Humphrey Lassell","workStartTime":"2022-04-13T18:47:41Z","workFinishedTime":"2022-01-23T06:39:08Z","todayWorkTime":8,"weeklyWorkTime":24,"_class":"com.guardjo.freeworkslackbot.domain.Worker"},
  {"_id":{"$oid":"636fccaffc13ae32540052d1"},"name":"Chelsy Sant","workStartTime":"2022-05-30T12:40:18Z","workFinishedTime":"2022-08-04T14:48:00Z","todayWorkTime":8,"weeklyWorkTime":37,"_class":"com.guardjo.freeworkslackbot.domain.Worker"},
  {"_id":{"$oid":"636fccaffc13ae32540052d2"},"name":"Giffie Ladon","workStartTime":"2022-07-21T07:47:55Z","workFinishedTime":"2022-05-27T01:56:56Z","todayWorkTime":6,"weeklyWorkTime":0,"_class":"com.guardjo.freeworkslackbot.domain.Worker"},
  {"_id":{"$oid":"636fccaffc13ae32540052d3"},"name":"Killie O'Collopy","workStartTime":"2022-10-04T10:53:24Z","workFinishedTime":"2022-10-15T21:14:22Z","todayWorkTime":8,"weeklyWorkTime":11,"_class":"com.guardjo.freeworkslackbot.domain.Worker"},
  {"_id":{"$oid":"636fccaffc13ae32540052d4"},"name":"Shelby Cardillo","workStartTime":"2022-09-18T13:39:07Z","workFinishedTime":"2022-03-20T23:27:25Z","todayWorkTime":9,"weeklyWorkTime":5,"_class":"com.guardjo.freeworkslackbot.domain.Worker"},
  {"_id":{"$oid":"636fccaffc13ae32540052d5"},"name":"Sileas Graffin","workStartTime":"2022-10-11T15:17:52Z","workFinishedTime":"2022-03-28T04:38:49Z","todayWorkTime":9,"weeklyWorkTime":8,"_class":"com.guardjo.freeworkslackbot.domain.Worker"},
  {"_id":{"$oid":"636fccaffc13ae32540052d6"},"name":"Reeba Wurst","workStartTime":"2022-05-08T01:18:34Z","workFinishedTime":"2022-03-05T14:36:58Z","todayWorkTime":8,"weeklyWorkTime":21,"_class":"com.guardjo.freeworkslackbot.domain.Worker"},
  {"_id":{"$oid":"636fccaffc13ae32540052d7"},"name":"Reade Niave","workStartTime":"2022-02-22T13:52:07Z","workFinishedTime":"2022-10-11T13:47:19Z","todayWorkTime":7,"weeklyWorkTime":18,"_class":"com.guardjo.freeworkslackbot.domain.Worker"},
  {"_id":{"$oid":"636fccaffc13ae32540052d8"},"name":"Bayard Auguste","workStartTime":"2022-04-13T21:51:37Z","workFinishedTime":"2022-07-21T22:36:54Z","todayWorkTime":6,"weeklyWorkTime":15,"_class":"com.guardjo.freeworkslackbot.domain.Worker"},
  {"_id":{"$oid":"636fccaffc13ae32540052d9"},"name":"Paolina Sloyan","workStartTime":"2022-09-05T15:55:23Z","workFinishedTime":"2022-09-17T10:02:11Z","todayWorkTime":7,"weeklyWorkTime":36,"_class":"com.guardjo.freeworkslackbot.domain.Worker"},
  {"_id":{"$oid":"636fccaffc13ae32540052da"},"name":"Nissie Coldbath","workStartTime":"2022-04-27T12:22:58Z","workFinishedTime":"2022-02-06T09:07:35Z","todayWorkTime":7,"weeklyWorkTime":36,"_class":"com.guardjo.freeworkslackbot.domain.Worker"},
  {"_id":{"$oid":"636fccaffc13ae32540052db"},"name":"Ivy MacIlhagga","workStartTime":"2022-07-11T06:37:40Z","workFinishedTime":"2022-05-29T18:04:44Z","todayWorkTime":10,"weeklyWorkTime":36,"_class":"com.guardjo.freeworkslackbot.domain.Worker"},
  {"_id":{"$oid":"636fccaffc13ae32540052dc"},"name":"Laney Muzzlewhite","workStartTime":"2022-03-20T09:28:07Z","workFinishedTime":"2022-07-16T16:58:42Z","todayWorkTime":7,"weeklyWorkTime":36,"_class":"com.guardjo.freeworkslackbot.domain.Worker"},
  {"_id":{"$oid":"636fccaffc13ae32540052dd"},"name":"Camala Ephson","workStartTime":"2021-11-18T06:32:59Z","workFinishedTime":"2022-08-26T10:28:38Z","todayWorkTime":8,"weeklyWorkTime":4,"_class":"com.guardjo.freeworkslackbot.domain.Worker"},
  {"_id":{"$oid":"636fccaffc13ae32540052de"},"name":"Babette Doag","workStartTime":"2021-11-15T22:06:20Z","workFinishedTime":"2022-09-03T20:47:13Z","todayWorkTime":6,"weeklyWorkTime":5,"_class":"com.guardjo.freeworkslackbot.domain.Worker"},
  {"_id":{"$oid":"636fccaffc13ae32540052df"},"name":"Ashton Kivits","workStartTime":"2022-07-01T04:52:31Z","workFinishedTime":"2022-02-12T06:56:18Z","todayWorkTime":7,"weeklyWorkTime":18,"_class":"com.guardjo.freeworkslackbot.domain.Worker"},
  {"_id":{"$oid":"636fccaffc13ae32540052e0"},"name":"Hilliard Lehrle","workStartTime":"2022-07-04T20:22:26Z","workFinishedTime":"2022-09-10T07:11:58Z","todayWorkTime":6,"weeklyWorkTime":1,"_class":"com.guardjo.freeworkslackbot.domain.Worker"},
  {"_id":{"$oid":"636fccaffc13ae32540052e1"},"name":"Agretha Mosson","workStartTime":"2022-07-15T04:22:39Z","workFinishedTime":"2022-06-23T01:03:56Z","todayWorkTime":8,"weeklyWorkTime":33,"_class":"com.guardjo.freeworkslackbot.domain.Worker"},
  {"_id":{"$oid":"636fccaffc13ae32540052e2"},"name":"Nelly Stinson","workStartTime":"2022-07-03T11:10:31Z","workFinishedTime":"2022-08-03T15:29:12Z","todayWorkTime":6,"weeklyWorkTime":28,"_class":"com.guardjo.freeworkslackbot.domain.Worker"},
  {"_id":{"$oid":"636fccaffc13ae32540052e3"},"name":"Kathye Durrans","workStartTime":"2022-03-07T07:13:29Z","workFinishedTime":"2022-01-20T03:07:37Z","todayWorkTime":10,"weeklyWorkTime":15,"_class":"com.guardjo.freeworkslackbot.domain.Worker"},
  {"_id":{"$oid":"636fccaffc13ae32540052e4"},"name":"Biron Billinge","workStartTime":"2021-11-21T21:33:40Z","workFinishedTime":"2022-11-06T17:56:02Z","todayWorkTime":9,"weeklyWorkTime":10,"_class":"com.guardjo.freeworkslackbot.domain.Worker"},
  {"_id":{"$oid":"636fccaffc13ae32540052e5"},"name":"Concettina Skones","workStartTime":"2022-02-07T02:27:48Z","workFinishedTime":"2022-08-05T20:40:37Z","todayWorkTime":10,"weeklyWorkTime":3,"_class":"com.guardjo.freeworkslackbot.domain.Worker"},
  {"_id":{"$oid":"636fccaffc13ae32540052e6"},"name":"Bill Kighly","workStartTime":"2022-04-10T15:10:18Z","workFinishedTime":"2022-06-01T21:16:10Z","todayWorkTime":9,"weeklyWorkTime":25,"_class":"com.guardjo.freeworkslackbot.domain.Worker"},
  {"_id":{"$oid":"636fccaffc13ae32540052e7"},"name":"Josephina Trodd","workStartTime":"2022-08-09T08:43:46Z","workFinishedTime":"2021-11-16T09:31:29Z","todayWorkTime":10,"weeklyWorkTime":25,"_class":"com.guardjo.freeworkslackbot.domain.Worker"},
  {"_id":{"$oid":"636fccaffc13ae32540052e8"},"name":"Ealasaid Muge","workStartTime":"2022-03-29T18:04:57Z","workFinishedTime":"2022-05-26T06:31:59Z","todayWorkTime":8,"weeklyWorkTime":31,"_class":"com.guardjo.freeworkslackbot.domain.Worker"},
  {"_id":{"$oid":"636fccaffc13ae32540052e9"},"name":"Yancey Trimming","workStartTime":"2022-02-02T13:59:22Z","workFinishedTime":"2022-10-08T05:56:02Z","todayWorkTime":10,"weeklyWorkTime":15,"_class":"com.guardjo.freeworkslackbot.domain.Worker"},
  {"_id":{"$oid":"636fccaffc13ae32540052ea"},"name":"Greer Sowden","workStartTime":"2022-02-25T20:51:08Z","workFinishedTime":"2022-07-23T02:14:18Z","todayWorkTime":8,"weeklyWorkTime":10,"_class":"com.guardjo.freeworkslackbot.domain.Worker"}]